getml_mlflow/__init__.py
getml_mlflow/autologging.py
getml_mlflow/constants.py
getml_mlflow/flavor.py
getml_mlflow/loggingconfiguration.py
getml_mlflow/data/__init__.py
getml_mlflow/data/dataframelike.py
getml_mlflow/data/getml_dataset.py
getml_mlflow/logging/__init__.py
getml_mlflow/logging/datacontainer.py
getml_mlflow/logging/function.py
getml_mlflow/logging/logger.py
getml_mlflow/logging/numpy.py
getml_mlflow/logging/pipeline.py
getml_mlflow/logging/systemmetrics.py
getml_mlflow/marshalling/__init__.py
getml_mlflow/marshalling/pipeline.py
getml_mlflow/patch/__init__.py
getml_mlflow/patch/engine.py
getml_mlflow/patch/pipeline.py
getml_mlflow/patch/project.py
getml_mlflow/util/__init__.py
getml_mlflow/util/callableenum.py
getml_mlflow/util/with_kwargs.py
getml_mlflow-0.1.2.dist-info/METADATA
getml_mlflow-0.1.2.dist-info/WHEEL
getml_mlflow-0.1.2.dist-info/RECORD
