Metadata-Version: 2.4
Name: getml-mlflow
Version: 0.1.2
Summary: Integrate MLflow into getML
Project-URL: API Reference, https://getml.com/dev/reference/mlflow/
Project-URL: User Guide, https://getml.com/dev/user_guide/concepts/mlflow_integration/
Project-URL: Repository, https://github.com/getml/getml-mlflow
Project-URL: Issues, https://github.com/getml/getml-mlflow/issues
Project-URL: getML, https://getml.com
Project-URL: Code17 GmbH, https://www.code17.io/
Project-URL: MLflow, https://mlflow.org/
Author-email: Code17 GmbH <hello@code17.io>, getML <hello@getml.com>
Maintainer-email: Code17 GmbH <hello@code17.io>, getML <hello@getml.com>
License-Expression: MIT
Keywords: AutoML,feature engineering,feature learning,getML,mlflow
Classifier: Development Status :: 4 - Beta
Classifier: Framework :: Pydantic
Classifier: Framework :: Pydantic :: 2
Classifier: Intended Audience :: Developers
Classifier: Intended Audience :: Education
Classifier: Intended Audience :: End Users/Desktop
Classifier: Intended Audience :: Financial and Insurance Industry
Classifier: Intended Audience :: Healthcare Industry
Classifier: Intended Audience :: Information Technology
Classifier: Intended Audience :: Manufacturing
Classifier: Intended Audience :: Other Audience
Classifier: Intended Audience :: Science/Research
Classifier: Intended Audience :: Telecommunications Industry
Classifier: License :: OSI Approved :: MIT License
Classifier: Natural Language :: English
Classifier: Operating System :: OS Independent
Classifier: Programming Language :: Python
Classifier: Programming Language :: Python :: 3.9
Classifier: Programming Language :: Python :: 3.10
Classifier: Programming Language :: Python :: 3.11
Classifier: Programming Language :: Python :: 3.12
Classifier: Programming Language :: Python :: Implementation :: CPython
Classifier: Programming Language :: Python :: Implementation :: PyPy
Classifier: Topic :: Office/Business
Classifier: Topic :: Scientific/Engineering
Classifier: Topic :: Scientific/Engineering :: Artificial Intelligence
Classifier: Topic :: Scientific/Engineering :: Information Analysis
Classifier: Topic :: Scientific/Engineering :: Visualization
Classifier: Topic :: Software Development :: Libraries :: Python Modules
Classifier: Topic :: System :: Logging
Classifier: Topic :: System :: Monitoring
Requires-Python: >=3.9
Requires-Dist: getml~=1.5.1
Requires-Dist: mlflow~=2.20.3
Requires-Dist: pyyaml~=6.0
Requires-Dist: typing-extensions>=4.12.2
